__init__.py
main.py
auth/__init__.py
auth/oauth.py
better_social_notifications-2.1.0.dist-info/licenses/LICENSE
models/__init__.py
models/models.py
notifications/__init__.py
notifications/notifications.py
util/__init__.py
util/healthcheck.py
util/logging.py
youtube/__init__.py
youtube/youtube.py
better_social_notifications-2.1.0.dist-info/METADATA
better_social_notifications-2.1.0.dist-info/WHEEL
better_social_notifications-2.1.0.dist-info/top_level.txt
better_social_notifications-2.1.0.dist-info/RECORD
