Metadata-Version: 2.4
Name: better-social-notifications
Version: 2.1.0
Summary: Python app to send notifications with lower latency from social networks like YouTube and Twitch
Author-email: jnstockley <jnstockley@users.noreply.github.com>
Project-URL: Homepage, https://github.com/jnstockley/bsn
Project-URL: Repository, https://github.com/jnstockley/bsn.git
Project-URL: Issues, https://github.com/jnstockley/bsn/issues
Keywords: starter,template,python
Classifier: Programming Language :: Python :: 3
Requires-Python: <3.15,>=3.14
License-File: LICENSE
Requires-Dist: apprise==1.9.7
Requires-Dist: google-api-python-client==2.188.0
Requires-Dist: peewee==3.19.0
Requires-Dist: python-dotenv==1.2.1
Dynamic: license-file
